test_poetry_binary_plugin/__init__.py
test_poetry_binary_plugin/main.py
test_poetry_binary_plugin/testing/__init__.py
test_poetry_binary_plugin/testing/testing.py
test_poetry_binary_plugin-0.0.3.dist-info/METADATA
test_poetry_binary_plugin-0.0.3.dist-info/WHEEL
test_poetry_binary_plugin-0.0.3.dist-info/entry_points.txt
test_poetry_binary_plugin-0.0.3.dist-info/RECORD
