Metadata-Version: 2.1
Name: test-poetry-binary-plugin
Version: 0.0.3
Summary: 
Author: Thomas Mahé
Author-email: contact@tmahe.dev
Requires-Python: >=3.10,<4.0
Classifier: Programming Language :: Python :: 3
Classifier: Programming Language :: Python :: 3.10
Classifier: Programming Language :: Python :: 3.11
Classifier: Programming Language :: Python :: 3.12
Provides-Extra: with-deps
Requires-Dist: rich (>=13.7.0,<14.0.0) ; extra == "with-deps"
